rangednumber/__init__.py
ranged_number-1.0.1.dist-info/LICENCE.txt
ranged_number-1.0.1.dist-info/METADATA
ranged_number-1.0.1.dist-info/WHEEL
ranged_number-1.0.1.dist-info/top_level.txt
ranged_number-1.0.1.dist-info/RECORD
